helga_pointing_poker/__init__.py
helga_pointing_poker/helga_pointing_poker.py
helga_pointing_poker-1.0.0.dist-info/DESCRIPTION.rst
helga_pointing_poker-1.0.0.dist-info/METADATA
helga_pointing_poker-1.0.0.dist-info/RECORD
helga_pointing_poker-1.0.0.dist-info/WHEEL
helga_pointing_poker-1.0.0.dist-info/entry_points.txt
helga_pointing_poker-1.0.0.dist-info/metadata.json
helga_pointing_poker-1.0.0.dist-info/top_level.txt
helga_pointing_poker-1.0.0.dist-info/zip-safe
tests/__init__.py
tests/test_pointing_poker.py
